<?xml version="1.0" encoding="utf-8" ?>
<Defs>

  <RecipeDef>
    <defName>Make_10xYeetBlade_Ula</defName>
    <label>make ula x10</label>
    <description>Make ula x10.</description>
    <jobString>Making ula x10.</jobString>
    <workAmount>1300</workAmount>
    <workSkill>Crafting</workSkill>
    <workSpeedStat>GeneralLaborSpeed</workSpeedStat>
    <effectWorking>Smith</effectWorking>
    <soundWorking>Recipe_MakeBow</soundWorking>
    <recipeUsers>
      <li>CraftingSpot</li>
      <li>FueledSmithy</li>
      <li>ElectricSmithy</li>
    </recipeUsers>
    <allowMixingIngredients>false</allowMixingIngredients>
    <ingredients>
      <li>
        <filter>
          <stuffCategoriesToAllow>
            <li>Metallic</li>
            <li>Woody</li>
          </stuffCategoriesToAllow>
        </filter>
        <count>30</count>
      </li>
    </ingredients>
    <fixedIngredientFilter>
      <stuffCategoriesToAllow>
        <li>Metallic</li>
        <li>Woody</li>
     </stuffCategoriesToAllow>
    </fixedIngredientFilter>
    <products>
      <YeetBlade_Ula>10</YeetBlade_Ula>
    </products>
  </RecipeDef>

</Defs>